run_remote_app/__init__.py
run_remote_app/cli.py
run_remote_app-0.1.1.dist-info/METADATA
run_remote_app-0.1.1.dist-info/WHEEL
run_remote_app-0.1.1.dist-info/entry_points.txt
run_remote_app-0.1.1.dist-info/top_level.txt
run_remote_app-0.1.1.dist-info/RECORD
