Metadata-Version: 2.4
Name: run-remote-app
Version: 0.1.1
Summary: Bootstrapper for remote-app from GitHub
Author-email: Nguyễn Dương <nguyenduongit89@gmail.com>
Requires-Python: >=3.7
